keywindinstaller/__init__.py
keywindinstaller/__main__.py
keywindinstaller/keywindinstaller.py
keywindinstaller-0.0.1.dist-info/LICENSE
keywindinstaller-0.0.1.dist-info/METADATA
keywindinstaller-0.0.1.dist-info/WHEEL
keywindinstaller-0.0.1.dist-info/top_level.txt
keywindinstaller-0.0.1.dist-info/RECORD
